CHANGES.txt
MANIFEST.in
README.md
setup.cfg
setup.py
pyramid_webassets/__init__.py
pyramid_webassets/tests/__init__.py
pyramid_webassets/tests/test_webassets.py
pyramid_webassets2.egg-info/PKG-INFO
pyramid_webassets2.egg-info/SOURCES.txt
pyramid_webassets2.egg-info/dependency_links.txt
pyramid_webassets2.egg-info/not-zip-safe
pyramid_webassets2.egg-info/requires.txt
pyramid_webassets2.egg-info/top_level.txt