Metadata-Version: 1.1
Name: pyramid-webassets2
Version: 0.7.2-fork-webassets2.1
Summary: pyramid_webassets
Home-page: http://github.com/sontek/pyramid_webassets
Author: John Anderson
Author-email: sontek@gmail.com
License: UNKNOWN
Keywords: web wsgi bfg pylons pyramid
Platform: UNKNOWN
Classifier: Programming Language :: Python
Classifier: Framework :: Pylons
Classifier: Topic :: Internet :: WWW/HTTP
Classifier: Topic :: Internet :: WWW/HTTP :: WSGI :: Application
